{
	"configurations" : 
	[
		{
			"directories" : 
			[
				{
					"build" : ".",
					"jsonFile" : "directory-.-Debug-d0094a50bb2071803777.json",
					"minimumCMakeVersion" : 
					{
						"string" : "3.27"
					},
					"projectIndex" : 0,
					"source" : ".",
					"targetIndexes" : 
					[
						0
					]
				}
			],
			"name" : "Debug",
			"projects" : 
			[
				{
					"directoryIndexes" : 
					[
						0
					],
					"name" : "BareboneClient",
					"targetIndexes" : 
					[
						0
					]
				}
			],
			"targets" : 
			[
				{
					"directoryIndex" : 0,
					"id" : "BareboneClient::@6890427a1f51a3e7e1df",
					"jsonFile" : "target-BareboneClient-Debug-25527d443fbc5d2615ac.json",
					"name" : "BareboneClient",
					"projectIndex" : 0
				}
			]
		}
	],
	"kind" : "codemodel",
	"paths" : 
	{
		"build" : "B:/work/C/TcpCppServer/BareboneClient/cmake-build-debug",
		"source" : "B:/work/C/TcpCppServer/BareboneClient"
	},
	"version" : 
	{
		"major" : 2,
		"minor" : 6
	}
}
